noahs_games/__init__.py
noahs_games/game_loader.py
noahs_games-0.1.6.dist-info/METADATA
noahs_games-0.1.6.dist-info/WHEEL
noahs_games-0.1.6.dist-info/top_level.txt
noahs_games-0.1.6.dist-info/RECORD
